{"nodes": [{"id": "home_istiaqfuad_desktop_last_bci_main_py", "label": "main.py", "file_type": "code", "source_file": "/home/istiaqfuad/Desktop/last-bci/main.py", "source_location": "L1"}, {"id": "last_bci_main_main", "label": "main()", "file_type": "code", "source_file": "/home/istiaqfuad/Desktop/last-bci/main.py", "source_location": "L1"}], "edges": [{"source": "home_istiaqfuad_desktop_last_bci_main_py", "target": "last_bci_main_main", "relation": "contains", "confidence": "EXTRACTED", "source_file": "/home/istiaqfuad/Desktop/last-bci/main.py", "source_location": "L1", "weight": 1.0}], "raw_calls": [{"caller_nid": "last_bci_main_main", "callee": "print", "is_member_call": false, "source_file": "/home/istiaqfuad/Desktop/last-bci/main.py", "source_location": "L2"}]}